<?xml version="1.0" encoding="UTF-8" standalone="yes"?>
<KeyValueMapOperations async="false" continueOnError="false" enabled="true" name="KVM-GetMisComprasTarget" mapIdentifier="CDP-targets">
    <DisplayName>KVM-GetMisComprasTarget</DisplayName>
    <Properties/>
    <ExclusiveCache>false</ExclusiveCache>
    <ExpiryTimeInSecs>300</ExpiryTimeInSecs>
    <Get assignTo="private.liv.target" index="1">
        <Key>
            <Parameter ref="miscompras-target"/>
        </Key>
    </Get>
    <Scope>environment</Scope>
</KeyValueMapOperations>